structured_agent/__init__.py
structured_agent/sql_agent.py
structured_agent/utils/__init__.py
structured_agent/utils/azure_embedding_utils.py
structured_agent/utils/config.ini
structured_agent/utils/conjur_utils.py
structured_agent/utils/constants_common.py
structured_agent/utils/constants_oracle.py
structured_agent/utils/constants_snowflake.py
structured_agent/utils/nodes.py
structured_agent/utils/sample_school_library_inventory.yaml
structured_agent/utils/services.py
structured_agent/utils/state.py
structured_agent/utils/tools.py
structured_sql_agent-0.1.0.dist-info/LICENSE
structured_sql_agent-0.1.0.dist-info/METADATA
structured_sql_agent-0.1.0.dist-info/WHEEL
structured_sql_agent-0.1.0.dist-info/entry_points.txt
structured_sql_agent-0.1.0.dist-info/top_level.txt
structured_sql_agent-0.1.0.dist-info/RECORD
