Metadata-Version: 2.2
Name: structured-sql-agent
Version: 0.1.0
Summary: A natural language to SQL query converter powered by LLMs.
Home-page: https://github.com/yourusername/sql-agent
Author: SQL-Agent Contributors
Author-email: sql-agent-team@example.com
Maintainer: Lead Developer Name
Maintainer-email: lead@example.com
Classifier: Programming Language :: Python :: 3
Classifier: Programming Language :: Python :: 3.8
Classifier: Programming Language :: Python :: 3.9
Classifier: Programming Language :: Python :: 3.10
Classifier: Programming Language :: Python :: 3.11
Classifier: Programming Language :: Python :: 3.12
Classifier: License :: OSI Approved :: MIT License
Classifier: Operating System :: OS Independent
Classifier: Development Status :: 3 - Alpha
Classifier: Intended Audience :: Developers
Classifier: Topic :: Database
Classifier: Topic :: Software Development :: Libraries :: Python Modules
Requires-Python: >=3.8
License-File: LICENSE
Requires-Dist: langchain_community==0.3.27
Requires-Dist: langchain_core==0.3.74
Requires-Dist: langchain_openai==0.3.29
Requires-Dist: langchain_google_genai==2.1.3
Requires-Dist: langchain_anthropic==0.3.8
Requires-Dist: langgraph==0.6.4
Requires-Dist: langsmith==0.4.13
Requires-Dist: python-dotenv==1.1.1
Requires-Dist: PyYAML==6.0.2
Requires-Dist: Requests==2.32.4
Requires-Dist: snowflake_connector_python==3.12.3
Requires-Dist: typing_extensions==4.14.1
Requires-Dist: certifi==2023.7.22
Requires-Dist: oracledb==2.2.1
Dynamic: author
Dynamic: author-email
Dynamic: classifier
Dynamic: description
Dynamic: description-content-type
Dynamic: home-page
Dynamic: maintainer
Dynamic: maintainer-email
Dynamic: requires-dist
Dynamic: requires-python
Dynamic: summary
